json_stream/__init__.py
json_stream/base.py
json_stream/iterators.py
json_stream/loader.py
json_stream/select_tokenizer.py
json_stream/tokenizer.py
json_stream/util.py
json_stream/visitor.py
json_stream/writer.py
json_stream/dump/__init__.py
json_stream/dump/threading.py
json_stream/dump/tests/__init__.py
json_stream/dump/tests/test_dump.py
json_stream/httpx/__init__.py
json_stream/httpx/tests/__init__.py
json_stream/httpx/tests/test_httpx.py
json_stream/requests/__init__.py
json_stream/requests/tests/__init__.py
json_stream/requests/tests/test_requests.py
json_stream/tests/__init__.py
json_stream/tests/test_buffering.py
json_stream/tests/test_collection_abcs.py
json_stream/tests/test_iterators.py
json_stream/tests/test_load_many.py
json_stream/tests/test_loader.py
json_stream/tests/test_tokenizer.py
json_stream/tests/test_tokenizer_integration.py
json_stream/tests/test_util.py
json_stream/tests/test_visit_many.py
json_stream/tests/test_visitor.py
json_stream/tests/test_writer.py
json_stream-2.4.1.dist-info/licenses/LICENSE.txt
json_stream-2.4.1.dist-info/METADATA
json_stream-2.4.1.dist-info/WHEEL
json_stream-2.4.1.dist-info/top_level.txt
json_stream-2.4.1.dist-info/RECORD
