Metadata-Version: 2.4
Name: json-stream
Version: 2.4.1
Summary: Streaming JSON encoder and decoder
Author-email: Jamie Cockburn <jamie_cockburn@hotmail.co.uk>
License: Copyright (c) 2020 Jamie Cockburn
Project-URL: Homepage, https://github.com/daggaz/json-stream
Project-URL: Repository, https://github.com/daggaz/json-stream
Project-URL: Tracker, https://github.com/daggaz/json-stream/issues
Project-URL: Funding, https://www.buymeacoffee.com/daggaz
Keywords: json,stream,decoder,encoder,parsing
Classifier: Development Status :: 5 - Production/Stable
Classifier: Intended Audience :: Developers
Classifier: Topic :: Software Development :: Libraries
Classifier: License :: OSI Approved :: MIT License
Classifier: Programming Language :: Python :: 3 :: Only
Classifier: Programming Language :: Python :: 3.8
Classifier: Programming Language :: Python :: 3.9
Classifier: Programming Language :: Python :: 3.10
Classifier: Programming Language :: Python :: 3.11
Classifier: Programming Language :: Python :: 3.12
Classifier: Programming Language :: Python :: 3.13
Classifier: Programming Language :: Python :: 3.14
Requires-Python: <4,>=3.5
License-File: LICENSE.txt
Requires-Dist: json-stream-rs-tokenizer>=0.4.17
Provides-Extra: requests
Requires-Dist: requests; extra == "requests"
Provides-Extra: httpx
Requires-Dist: httpx; extra == "httpx"
Dynamic: license-file
